LICENSE
README.md
setup.py
pymedia/__init__.py
pymedia/audio/__init__.py
pymedia/audio/audio.py
python_pymedia.egg-info/PKG-INFO
python_pymedia.egg-info/SOURCES.txt
python_pymedia.egg-info/dependency_links.txt
python_pymedia.egg-info/top_level.txt