Metadata-Version: 2.1
Name: python-pymedia
Version: 1.0.0
Summary: Package to handle and process media
Home-page: https://github.com/simplyrohan/pymedia
Author: Rohan Gupta
License: UNKNOWN
Platform: UNKNOWN
Classifier: Programming Language :: Python :: 3
Classifier: License :: OSI Approved :: MIT License
Classifier: Operating System :: OS Independent
Requires-Python: >=3.6
License-File: LICENSE
